a5dev/__init__.py
a5dev/deepfake.py
a5dev/general.py
a5dev/image.py
a5dev/transfersh.py
a5dev/video.py
a5dev-0.9.2.dist-info/LICENSE
a5dev-0.9.2.dist-info/METADATA
a5dev-0.9.2.dist-info/WHEEL
a5dev-0.9.2.dist-info/top_level.txt
a5dev-0.9.2.dist-info/RECORD
