Metadata-Version: 2.1
Name: a5dev
Version: 0.9.2
Summary: Helper library for day to day task in a ml engineer's life.
Home-page: https://github.com/ankitsainidev/a5dev
Author: Ankit Saini
Author-email: ankitsaini100205@gmail.com
License: UNKNOWN
Platform: UNKNOWN
Classifier: Programming Language :: Python :: 3
Classifier: License :: OSI Approved :: MIT License
Classifier: Operating System :: OS Independent
Requires-Python: >=3.5
Requires-Dist: numpy
Requires-Dist: opencv-python
Requires-Dist: kaggle
Requires-Dist: torch (>=1.0.0)
Requires-Dist: wget
Requires-Dist: requests
